ec2_old_snapshots/ec2_old_snapshots/ec2_old_snapshots.py
ec2_old_snapshots/ec2_old_snapshots/ec2_old_snapshots.rego
ec2_old_snapshots/ec2_old_snapshots/manifest.toml
ec2_old_snapshots/ec2_old_snapshots/test_old_snapshots.py
idle_instances/idle_instances/idle_instances.py
idle_instances/idle_instances/idle_instances.rego
idle_instances/idle_instances/manifest.toml
idle_instances/idle_instances/test_idle_instances.py
stray_ebs/stray_ebs/manifest.toml
stray_ebs/stray_ebs/stray_ebs.py
stray_ebs/stray_ebs/stray_ebs.rego
stray_ebs/stray_ebs/test_stray_ebs.py
unattached_eips/unattached_eips/manifest.toml
unattached_eips/unattached_eips/test_unattached_eips.py
unattached_eips/unattached_eips/unattached_eips.py
unattached_eips/unattached_eips/unattached_eips.rego
opsbox_ec2_checks-0.2.0.dist-info/LICENCE.txt
opsbox_ec2_checks-0.2.0.dist-info/METADATA
opsbox_ec2_checks-0.2.0.dist-info/WHEEL
opsbox_ec2_checks-0.2.0.dist-info/entry_points.txt
opsbox_ec2_checks-0.2.0.dist-info/top_level.txt
opsbox_ec2_checks-0.2.0.dist-info/RECORD
