Metadata-Version: 2.2
Name: opsbox-ec2-checks
Version: 0.2.0
Summary: Collection of EC2 checks for opsbox.
License: Mozilla Public License Version 2.0
Requires-Python: ==3.11.*
License-File: LICENCE.txt
Requires-Dist: opsbox-ec2-provider>=0.1.3
Requires-Dist: opsbox-rego-handler>=0.2.0
